open_codex/agent_builder.py
open_codex/main.py
open_codex/agents/__init__.py
open_codex/agents/phi_4_mini.py
open_codex/interfaces/__init__.py
open_codex/interfaces/llm_agent.py
open_codex/resources/__init__.py
open_codex/resources/prompt.txt
open_codex-0.1.15.dist-info/licenses/LICENSE.md
open_codex-0.1.15.dist-info/METADATA
open_codex-0.1.15.dist-info/WHEEL
open_codex-0.1.15.dist-info/entry_points.txt
open_codex-0.1.15.dist-info/top_level.txt
open_codex-0.1.15.dist-info/RECORD
