Metadata-Version: 2.4
Name: open_codex
Version: 0.1.15
Summary: AI CLI with OSS LLM integration
Requires-Python: >=3.11
License-File: LICENSE.md
Requires-Dist: huggingface-hub>=0.30.2
Requires-Dist: llama-cpp-python>=0.3.8
Requires-Dist: prompt_toolkit
Requires-Dist: pyperclip>=1.9.0
Dynamic: license-file
